README.md
setup.cfg
setup.py
robics/__init__.py
robics/robust_topics.py
robics.egg-info/PKG-INFO
robics.egg-info/SOURCES.txt
robics.egg-info/dependency_links.txt
robics.egg-info/requires.txt
robics.egg-info/top_level.txt